doddvlib/__init__.py
doddvlib-0.0.1.dist-info/METADATA
doddvlib-0.0.1.dist-info/WHEEL
doddvlib-0.0.1.dist-info/top_level.txt
doddvlib-0.0.1.dist-info/RECORD
