Metadata-Version: 2.1
Name: doddvlib
Version: 0.0.1
Summary: redacted
Home-page: http://try.microchip.com
Author: Microchip Technology
Author-email: support@microchip.com
License: UNKNOWN
Platform: UNKNOWN
Classifier: Programming Language :: Python :: 3
Requires-Python: >=3.6
